LICENSE
readme.md
.trunk/plugins/trunk/LICENSE
packages/hacs-api/src/hacs_api/main.py
packages/hacs-cli/main.py
healthcare_hacs-0.2.2.dist-info/METADATA
healthcare_hacs-0.2.2.dist-info/WHEEL
healthcare_hacs-0.2.2.dist-info/licenses/LICENSE
healthcare_hacs-0.2.2.dist-info/RECORD
