Metadata-Version: 2.4
Name: healthcare-hacs
Version: 0.2.2
Summary: Healthcare Agent Communication Standard - Production-ready multi-package workspace
Project-URL: Homepage, https://github.com/solanovisitor/hacs
Project-URL: Documentation, https://github.com/solanovisitor/hacs/blob/main/docs/README.md
Project-URL: Repository, https://github.com/solanovisitor/hacs
Project-URL: Bug Tracker, https://github.com/solanovisitor/hacs/issues
Project-URL: Changelog, https://github.com/solanovisitor/hacs/blob/main/docs/reference/changelog.md
Author-email: Solano Todeschini <solano.todeschini@gmail.com>
Maintainer-email: Solano Todeschini <solano.todeschini@gmail.com>
License: Apache-2.0
License-File: LICENSE
Keywords: agents,ai,clinical,communication,fhir,healthcare,interoperability,standard
Classifier: Development Status :: 5 - Production/Stable
Classifier: Intended Audience :: Developers
Classifier: Intended Audience :: Healthcare Industry
Classifier: License :: OSI Approved :: Apache Software License
Classifier: Programming Language :: Python :: 3
Classifier: Programming Language :: Python :: 3.10
Classifier: Programming Language :: Python :: 3.11
Classifier: Programming Language :: Python :: 3.12
Classifier: Programming Language :: Python :: 3.13
Classifier: Topic :: Internet :: WWW/HTTP :: Dynamic Content
Classifier: Topic :: Scientific/Engineering :: Medical Science Apps.
Classifier: Topic :: Software Development :: Libraries :: Python Modules
Classifier: Typing :: Typed
Requires-Python: >=3.10
Requires-Dist: anthropic>=0.57.1
Requires-Dist: google-generativeai>=0.8.5
Requires-Dist: hacs-anthropic
Requires-Dist: hacs-api>=0.2.2
Requires-Dist: hacs-cli>=0.2.2
Requires-Dist: hacs-core>=0.2.2
Requires-Dist: hacs-fhir>=0.2.2
Requires-Dist: hacs-models>=0.2.2
Requires-Dist: hacs-openai
Requires-Dist: hacs-tools>=0.2.2
Requires-Dist: langchain-core>=0.3.66
Requires-Dist: langgraph>=0.5.0
Requires-Dist: openai>=1.93.0
Requires-Dist: pinecone>=7.3.0
Requires-Dist: python-dotenv>=1.1.1
Requires-Dist: qdrant-client>=1.14.3
Requires-Dist: rich>=14.0.0
Provides-Extra: all
Requires-Dist: hacs-anthropic>=0.1.0; extra == 'all'
Requires-Dist: hacs-openai>=0.1.0; extra == 'all'
Requires-Dist: hacs-pinecone>=0.1.0; extra == 'all'
Requires-Dist: hacs-qdrant>=0.1.0; extra == 'all'
Requires-Dist: instructor>=1.0.0; extra == 'all'
Requires-Dist: psutil>=5.9.0; extra == 'all'
Requires-Dist: sentence-transformers>=2.2.0; extra == 'all'
Provides-Extra: dev
Requires-Dist: pyright>=1.1.0; extra == 'dev'
Requires-Dist: pytest-asyncio>=0.21.0; extra == 'dev'
Requires-Dist: pytest-cov>=4.0.0; extra == 'dev'
Requires-Dist: pytest>=7.0.0; extra == 'dev'
Requires-Dist: ruff>=0.4.0; extra == 'dev'
Provides-Extra: examples
Requires-Dist: psutil>=5.9.0; extra == 'examples'
Provides-Extra: llm-all
Requires-Dist: hacs-anthropic>=0.2.2; extra == 'llm-all'
Requires-Dist: hacs-openai>=0.2.2; extra == 'llm-all'
Requires-Dist: instructor>=1.0.0; extra == 'llm-all'
Provides-Extra: llm-anthropic
Requires-Dist: hacs-anthropic>=0.2.2; extra == 'llm-anthropic'
Provides-Extra: llm-openai
Requires-Dist: hacs-openai>=0.2.2; extra == 'llm-openai'
Requires-Dist: instructor>=1.0.0; extra == 'llm-openai'
Provides-Extra: vectorization-all
Requires-Dist: hacs-anthropic>=0.1.0; extra == 'vectorization-all'
Requires-Dist: hacs-openai>=0.1.0; extra == 'vectorization-all'
Requires-Dist: hacs-pinecone>=0.1.0; extra == 'vectorization-all'
Requires-Dist: hacs-qdrant>=0.1.0; extra == 'vectorization-all'
Requires-Dist: sentence-transformers>=2.2.0; extra == 'vectorization-all'
Provides-Extra: vectorization-anthropic
Requires-Dist: hacs-anthropic>=0.1.0; extra == 'vectorization-anthropic'
Requires-Dist: hacs-qdrant>=0.1.0; extra == 'vectorization-anthropic'
Provides-Extra: vectorization-openai
Requires-Dist: hacs-openai>=0.1.0; extra == 'vectorization-openai'
Requires-Dist: hacs-qdrant>=0.1.0; extra == 'vectorization-openai'
Provides-Extra: vectorization-pinecone
Requires-Dist: hacs-openai>=0.1.0; extra == 'vectorization-pinecone'
Requires-Dist: hacs-pinecone>=0.1.0; extra == 'vectorization-pinecone'
Provides-Extra: vectorization-qdrant
Requires-Dist: hacs-qdrant>=0.1.0; extra == 'vectorization-qdrant'
Requires-Dist: sentence-transformers>=2.2.0; extra == 'vectorization-qdrant'
Provides-Extra: viz
Requires-Dist: pygraphviz>=1.11; extra == 'viz'
